canalyse/__init__.py
canalyse/_version.py
canalyse/cli.py
canalyse/parser.py
canalyse/validator.py
test/__init__.py
test/test_cli.py
test/test_parser.py
test/test_validator.py
canalyse-0.0.6.dist-info/LICENSE
canalyse-0.0.6.dist-info/METADATA
canalyse-0.0.6.dist-info/WHEEL
canalyse-0.0.6.dist-info/entry_points.txt
canalyse-0.0.6.dist-info/top_level.txt
canalyse-0.0.6.dist-info/RECORD
